ern_reactor.py
ern_reactor-0.2.3.dist-info/METADATA
ern_reactor-0.2.3.dist-info/WHEEL
ern_reactor-0.2.3.dist-info/top_level.txt
ern_reactor-0.2.3.dist-info/RECORD
