Metadata-Version: 2.1
Name: ern-reactor
Version: 0.2.3
Summary: Do arbitrary things in reaction to Ercoin transfers
Home-page: https://github.com/KrzysiekJ/ern_reactor
Author: Krzysztof Jurewicz
Author-email: krzysztof.jurewicz@gmail.com
License: UNKNOWN
Keywords: cryptocurrency
Platform: UNKNOWN
Classifier: Development Status :: 3 - Alpha
Classifier: Framework :: AsyncIO
Classifier: Intended Audience :: Developers
Classifier: Intended Audience :: Financial and Insurance Industry
Classifier: License :: OSI Approved :: Apache Software License
Classifier: Operating System :: MacOS :: MacOS X
Classifier: Operating System :: Microsoft :: Windows
Classifier: Operating System :: POSIX
Classifier: Programming Language :: Python :: 3.8
Classifier: Topic :: Internet
Classifier: Topic :: Software Development :: Libraries :: Python Modules
Requires-Python: >=3.8, <4
Requires-Dist: python-dateutil (<3,>=2)
Requires-Dist: websockets (<10,>=9)
